sparrow_flir/__init__.py
sparrow_flir/thermal_extractor.py
sparrow_flir/thermal_extractor_test.py
sparrow_flir-0.1.1.dist-info/LICENSE
sparrow_flir-0.1.1.dist-info/WHEEL
sparrow_flir-0.1.1.dist-info/METADATA
sparrow_flir-0.1.1.dist-info/RECORD
