Metadata-Version: 2.1
Name: sparrow-flir
Version: 0.1.1
Summary: 
License: CC0-1.0
Author: Sparrow Computing
Author-email: ben@sparrow.dev
Requires-Python: >=3.8,<3.11
Classifier: License :: CC0 1.0 Universal (CC0 1.0) Public Domain Dedication
Classifier: Programming Language :: Python :: 3
Classifier: Programming Language :: Python :: 3.10
Classifier: Programming Language :: Python :: 3.8
Classifier: Programming Language :: Python :: 3.9
Requires-Dist: Pillow (>=9.2.0,<10.0.0)
Requires-Dist: numpy (>=1.23.2,<2.0.0)
